[
  {
    "id": "pol-001",
    "policyNumber": "AUTO-2023-001",
    "customerId": "cust-001",
    "type": "auto",
    "status": "active",
    "premium": 1250.00,
    "coverage": 500000,
    "deductible": 500,
    "startDate": "2023-01-15T00:00:00Z",
    "endDate": "2024-01-15T00:00:00Z",
    "renewalDate": "2024-01-15T00:00:00Z",
    "createdAt": "2023-01-15T10:00:00Z",
    "updatedAt": "2023-01-15T10:00:00Z"
  },
  {
    "id": "pol-002",
    "policyNumber": "HOME-2023-045",
    "customerId": "cust-002",
    "type": "home",
    "status": "active",
    "premium": 2100.00,
    "coverage": 750000,
    "deductible": 1000,
    "startDate": "2023-06-20T00:00:00Z",
    "endDate": "2024-06-20T00:00:00Z",
    "renewalDate": "2024-06-20T00:00:00Z",
    "createdAt": "2023-06-20T14:22:00Z",
    "updatedAt": "2023-06-20T14:22:00Z"
  },
  {
    "id": "pol-003",
    "policyNumber": "LIFE-2023-089",
    "customerId": "cust-003",
    "type": "life",
    "status": "active",
    "premium": 850.00,
    "coverage": 1000000,
    "deductible": 0,
    "startDate": "2023-09-10T00:00:00Z",
    "endDate": "2043-09-10T00:00:00Z",
    "renewalDate": "2024-09-10T00:00:00Z",
    "createdAt": "2023-09-10T09:15:00Z",
    "updatedAt": "2023-09-10T09:15:00Z"
  },
  {
    "id": "pol-004",
    "policyNumber": "AUTO-2023-112",
    "customerId": "cust-004",
    "type": "auto",
    "status": "active",
    "premium": 980.00,
    "coverage": 300000,
    "deductible": 750,
    "startDate": "2023-11-05T00:00:00Z",
    "endDate": "2024-11-05T00:00:00Z",
    "renewalDate": "2024-11-05T00:00:00Z",
    "createdAt": "2023-11-05T16:30:00Z",
    "updatedAt": "2023-11-05T16:30:00Z"
  },
  {
    "id": "pol-005",
    "policyNumber": "HOME-2022-198",
    "customerId": "cust-005",
    "type": "home",
    "status": "lapsed",
    "premium": 3200.00,
    "coverage": 1200000,
    "deductible": 2000,
    "startDate": "2022-03-18T00:00:00Z",
    "endDate": "2023-03-18T00:00:00Z",
    "renewalDate": "2023-03-18T00:00:00Z",
    "createdAt": "2022-03-18T11:45:00Z",
    "updatedAt": "2023-04-01T09:00:00Z"
  },
  {
    "id": "pol-006",
    "policyNumber": "AUTO-2023-245",
    "customerId": "cust-006",
    "type": "auto",
    "status": "active",
    "premium": 720.00,
    "coverage": 250000,
    "deductible": 500,
    "startDate": "2023-07-22T00:00:00Z",
    "endDate": "2024-07-22T00:00:00Z",
    "renewalDate": "2024-07-22T00:00:00Z",
    "createdAt": "2023-07-22T13:20:00Z",
    "updatedAt": "2023-07-22T13:20:00Z"
  },
  {
    "id": "pol-007",
    "policyNumber": "LIFE-2024-012",
    "customerId": "cust-007",
    "type": "life",
    "status": "active",
    "premium": 450.00,
    "coverage": 500000,
    "deductible": 0,
    "startDate": "2024-01-10T00:00:00Z",
    "endDate": "2044-01-10T00:00:00Z",
    "renewalDate": "2025-01-10T00:00:00Z",
    "createdAt": "2024-01-10T10:00:00Z",
    "updatedAt": "2024-01-10T10:00:00Z"
  },
  {
    "id": "pol-008",
    "policyNumber": "HOME-2023-320",
    "customerId": "cust-008",
    "type": "home",
    "status": "active",
    "premium": 1800.00,
    "coverage": 650000,
    "deductible": 1500,
    "startDate": "2023-04-15T00:00:00Z",
    "endDate": "2024-04-15T00:00:00Z",
    "renewalDate": "2024-04-15T00:00:00Z",
    "createdAt": "2023-04-15T08:30:00Z",
    "updatedAt": "2023-04-15T08:30:00Z"
  },
  {
    "id": "pol-009",
    "policyNumber": "AUTO-2024-003",
    "customerId": "cust-001",
    "type": "auto",
    "status": "cancelled",
    "premium": 1150.00,
    "coverage": 400000,
    "deductible": 500,
    "startDate": "2024-01-15T00:00:00Z",
    "endDate": "2025-01-15T00:00:00Z",
    "renewalDate": "2025-01-15T00:00:00Z",
    "createdAt": "2024-01-15T10:30:00Z",
    "updatedAt": "2024-03-20T14:00:00Z"
  },
  {
    "id": "pol-010",
    "policyNumber": "AUTO-2023-178",
    "customerId": "cust-002",
    "type": "auto",
    "status": "active",
    "premium": 1100.00,
    "coverage": 350000,
    "deductible": 500,
    "startDate": "2023-08-01T00:00:00Z",
    "endDate": "2024-08-01T00:00:00Z",
    "renewalDate": "2024-08-01T00:00:00Z",
    "createdAt": "2023-08-01T09:00:00Z",
    "updatedAt": "2023-08-01T09:00:00Z"
  }
]
